{
	"system" : {
		"platform" : "windows64",
		"os_name" : "Windows 10",
		"os_version" : "10.0"
	},
	"error" : {
		"executable" : "quartus",
		"comment" : "none",
		"error_message" : "Access Violation at 0X00000000615871B0",
		"source_file" : "unknown",
		"line" : "0",
		"stack_trace" : "\t 0x615871af: QtGui4 + 0x871af (?winMouseButtonUp@QApplication@@SAXXZ + 0x85f)\n\t0x7ff84cd56d40: USER32 + 0x16d40 (CallWindowProcW + 0x4c0)\n\t0x7ff84cd56a1b: USER32 + 0x16a1b (CallWindowProcW + 0x19b)\n\t0x7ff84cd604d2: USER32 + 0x204d2 (IsWindowVisible + 0x1a2)\n\t0x7ff84deae6b3: ntdll + 0x9e6b3 (KiUserCallbackDispatcher + 0x23)\n\t0x7ff84aeb10a3: win32u + 0x10a3 (NtUserPeekMessage + 0x13)\n\t0x7ff84cd586b2: USER32 + 0x186b2 (PeekMessageW + 0x172)\n\t0x7ff84cd58644: USER32 + 0x18644 (PeekMessageW + 0x104)\n\t 0x61342663: QtCore4 + 0x132663 (?processEvents@QEventDispatcherWin32@@UEAA_NV?$QFlags@W4ProcessEventsFlag@QEventLoop@@@@@Z + 0x243)\n\t 0x61580eb4: QtGui4 + 0x80eb4 (?openPopup@QApplicationPrivate@@QEAAXPEAVQWidget@@@Z + 0x204)\n\t 0x6131a88b: QtCore4 + 0x10a88b (?exec@QEventLoop@@QEAAHV?$QFlags@W4ProcessEventsFlag@QEventLoop@@@@@Z + 0x22b)\n\t 0x61923660: QtGui4 + 0x423660 (?exec@QDialog@@QEAAHXZ + 0xf0)\n\t0x7ff81b90b46a: GCL_AFCQ + 0xab46a (?internal_error_display@AFCQ_MSG_DISPLAY@@UEAAXV?$basic_string@DU?$char_traits@D@std@@V?$allocator@D@2@@std@@@Z + 0x27a)\n\t0x7ff8386dd7b3: CCL_MSG + 0x1d7b3 (?internal_error@MSG_REPORT@@UEAAXAEBV?$basic_string@DU?$char_traits@D@std@@V?$allocator@D@2@@std@@@Z + 0xe3)\n\t0x7ff8386f7c17: CCL_MSG + 0x37c17 (?finalize@MSG_ERROR_INFO@@QEAAXXZ + 0x87)\n\t0x7ff8386f876d: CCL_MSG + 0x3876d (?report_fatal@MSG_INTERNAL_ERROR@@SAXPEBDPEAX@Z + 0x15d)\n\t0x7ff8384d44f0: CCL_ERR + 0x44f0 (?err_report_fatal_exception@@YAXPEBDPEAX@Z + 0x70)\n\t0x7ff8384d4379: CCL_ERR + 0x4379 (?err_handle_fatal_exception@@YAJPEAU_EXCEPTION_POINTERS@@@Z + 0xb9)\n\t0x7ff84a60bdcf: KERNELBASE + 0xebdcf (UnhandledExceptionFilter + 0x18f)\n\t0x7ff84dedbb50: ntdll + 0xcbb50 (LdrResolveDelayLoadsFromDll + 0xa70)\n\t0x7ff84deae61f: ntdll + 0x9e61f (KiUserApcDispatcher + 0x9f)\n\t0x7ff84deaf7dc: ntdll + 0x9f7dc (__chkstk + 0x11c)\n\t0x7ff84de1d855: ntdll + 0xd855 (RtlWalkFrameChain + 0x13f5)\n\t0x7ff84deae70d: ntdll + 0x9e70d (KiUserExceptionDispatcher + 0x2d)\n\t 0x615871af: QtGui4 + 0x871af (?winMouseButtonUp@QApplication@@SAXXZ + 0x85f)\n\t0x7ff84cd56d40: USER32 + 0x16d40 (CallWindowProcW + 0x4c0)\n\t0x7ff84cd56a1b: USER32 + 0x16a1b (CallWindowProcW + 0x19b)\n\t0x7ff84cd604d2: USER32 + 0x204d2 (IsWindowVisible + 0x1a2)\n\t0x7ff84deae6b3: ntdll + 0x9e6b3 (KiUserCallbackDispatcher + 0x23)\n\t0x7ff84aeb1b63: win32u + 0x1b63 (NtUserShowWindow + 0x13)\n\t 0x6159668d: QtGui4 + 0x9668d (?hide_sys@QWidgetPrivate@@QEAAXXZ + 0x3d)\n\t 0x615628cb: QtGui4 + 0x628cb (?hide_helper@QWidgetPrivate@@QEAAXXZ + 0x12b)\n\t 0x6156f622: QtGui4 + 0x6f622 (?setVisible@QWidget@@UEAAX_N@Z + 0x4b2)\n\t 0x619244ac: QtGui4 + 0x4244ac (?setVisible@QDialog@@UEAAX_N@Z + 0x24c)\n\t 0x619234df: QtGui4 + 0x4234df (?done@QDialog@@UEAAXH@Z + 0x1f)\n\t0x7ff81b903048: GCL_AFCQ + 0xa3048 (?send_report@AFCQ_CRASH_REPORTER_DLG@@IEAAXXZ + 0x168)\n\t 0x6132c420: QtCore4 + 0x11c420 (?activate@QMetaObject@@SAXPEAVQObject@@PEBU1@HPEAPEAX@Z + 0x520)\n\t 0x61a8c682: QtGui4 + 0x58c682 (?clicked@QAbstractButton@@IEAAX_N@Z + 0x32)\n\t 0x61843d9e: QtGui4 + 0x343d9e (?click@QAbstractButton@@QEAAXXZ + 0x51e)\n\t 0x61843a17: QtGui4 + 0x343a17 (?click@QAbstractButton@@QEAAXXZ + 0x197)\n\t 0x61844899: QtGui4 + 0x344899 (?mouseReleaseEvent@QAbstractButton@@MEAAXPEAVQMouseEvent@@@Z + 0x59)\n\t 0x61560794: QtGui4 + 0x60794 (?event@QWidget@@MEAA_NPEAVQEvent@@@Z + 0xd4)\n\t 0x61522e95: QtGui4 + 0x22e95 (?notify_helper@QApplicationPrivate@@QEAA_NPEAVQObject@@PEAVQEvent@@@Z + 0xf5)\n\t 0x61521a8e: QtGui4 + 0x21a8e (?notify@QApplication@@UEAA_NPEAVQObject@@PEAVQEvent@@@Z + 0x71e)\n\t 0x6131d92b: QtCore4 + 0x10d92b (?notifyInternal@QCoreApplication@@AEAA_NPEAVQObject@@PEAVQEvent@@@Z + 0x7b)\n\t 0x61525cfe: QtGui4 + 0x25cfe (?sendMouseEvent@QApplicationPrivate@@SA_NPEAVQWidget@@PEAVQMouseEvent@@00PEAPEAV2@AEAV?$QPointer@VQWidget@@@@_N@Z + 0x1de)\n\t 0x615856f0: QtGui4 + 0x856f0 (?trUtf8@QScrollBar@@SA?AVQString@@PEBD0H@Z + 0x1440)\n\t 0x615890b1: QtGui4 + 0x890b1 (?winMouseButtonUp@QApplication@@SAXXZ + 0x2761)\n\t0x7ff84cd56d40: USER32 + 0x16d40 (CallWindowProcW + 0x4c0)\n\t0x7ff84cd56712: USER32 + 0x16712 (DispatchMessageW + 0x1d2)\n\t 0x61342802: QtCore4 + 0x132802 (?processEvents@QEventDispatcherWin32@@UEAA_NV?$QFlags@W4ProcessEventsFlag@QEventLoop@@@@@Z + 0x3e2)\n\t 0x61580eb4: QtGui4 + 0x80eb4 (?openPopup@QApplicationPrivate@@QEAAXPEAVQWidget@@@Z + 0x204)\n\t 0x6131a88b: QtCore4 + 0x10a88b (?exec@QEventLoop@@QEAAHV?$QFlags@W4ProcessEventsFlag@QEventLoop@@@@@Z + 0x22b)\n\t 0x61923660: QtGui4 + 0x423660 (?exec@QDialog@@QEAAHXZ + 0xf0)\n\t0x7ff81b90b46a: GCL_AFCQ + 0xab46a (?internal_error_display@AFCQ_MSG_DISPLAY@@UEAAXV?$basic_string@DU?$char_traits@D@std@@V?$allocator@D@2@@std@@@Z + 0x27a)\n\t0x7ff8386dd7b3: CCL_MSG + 0x1d7b3 (?internal_error@MSG_REPORT@@UEAAXAEBV?$basic_string@DU?$char_traits@D@std@@V?$allocator@D@2@@std@@@Z + 0xe3)\n\t0x7ff8386f7c17: CCL_MSG + 0x37c17 (?finalize@MSG_ERROR_INFO@@QEAAXXZ + 0x87)\n\t0x7ff8386f876d: CCL_MSG + 0x3876d (?report_fatal@MSG_INTERNAL_ERROR@@SAXPEBDPEAX@Z + 0x15d)\n\t0x7ff8384d44f0: CCL_ERR + 0x44f0 (?err_report_fatal_exception@@YAXPEBDPEAX@Z + 0x70)\n\t0x7ff8384d4379: CCL_ERR + 0x4379 (?err_handle_fatal_exception@@YAJPEAU_EXCEPTION_POINTERS@@@Z + 0xb9)\n\t0x7ff84a60bdcf: KERNELBASE + 0xebdcf (UnhandledExceptionFilter + 0x18f)\n\t0x7ff84dedbb50: ntdll + 0xcbb50 (LdrResolveDelayLoadsFromDll + 0xa70)\n\t0x7ff84deae61f: ntdll + 0x9e61f (KiUserApcDispatcher + 0x9f)\n\t0x7ff84deaf7dc: ntdll + 0x9f7dc (__chkstk + 0x11c)\n\t0x7ff84de1d855: ntdll + 0xd855 (RtlWalkFrameChain + 0x13f5)\n\t0x7ff84deae70d: ntdll + 0x9e70d (KiUserExceptionDispatcher + 0x2d)\n\t 0x615871af: QtGui4 + 0x871af (?winMouseButtonUp@QApplication@@SAXXZ + 0x85f)\n\t0x7ff84cd56d40: USER32 + 0x16d40 (CallWindowProcW + 0x4c0)\n\t0x7ff84cd56a1b: USER32 + 0x16a1b (CallWindowProcW + 0x19b)\n\t0x7ff84cd604d2: USER32 + 0x204d2 (IsWindowVisible + 0x1a2)\n\t0x7ff84deae6b3: ntdll + 0x9e6b3 (KiUserCallbackDispatcher + 0x23)\n\t0x7ff84aeb1b63: win32u + 0x1b63 (NtUserShowWindow + 0x13)\n\t 0x6159668d: QtGui4 + 0x9668d (?hide_sys@QWidgetPrivate@@QEAAXXZ + 0x3d)\n\t 0x615628cb: QtGui4 + 0x628cb (?hide_helper@QWidgetPrivate@@QEAAXXZ + 0x12b)\n\t 0x6156f622: QtGui4 + 0x6f622 (?setVisible@QWidget@@UEAAX_N@Z + 0x4b2)\n\t 0x619244ac: QtGui4 + 0x4244ac (?setVisible@QDialog@@UEAAX_N@Z + 0x24c)\n\t 0x619234df: QtGui4 + 0x4234df (?done@QDialog@@UEAAXH@Z + 0x1f)\n\t 0x6192315d: QtGui4 + 0x42315d (?closeEvent@QDialog@@MEAAXPEAVQCloseEvent@@@Z + 0x5d)\n\t 0x61560be1: QtGui4 + 0x60be1 (?event@QWidget@@MEAA_NPEAVQEvent@@@Z + 0x521)\n\t 0x61522e95: QtGui4 + 0x22e95 (?notify_helper@QApplicationPrivate@@QEAA_NPEAVQObject@@PEAVQEvent@@@Z + 0xf5)\n\t 0x61522b2f: QtGui4 + 0x22b2f (?notify@QApplication@@UEAA_NPEAVQObject@@PEAVQEvent@@@Z + 0x17bf)\n\t 0x6131d92b: QtCore4 + 0x10d92b (?notifyInternal@QCoreApplication@@AEAA_NPEAVQObject@@PEAVQEvent@@@Z + 0x7b)\n\t 0x6155e258: QtGui4 + 0x5e258 (?close_helper@QWidgetPrivate@@QEAA_NW4CloseMode@1@@Z + 0xa8)\n\t 0x61587956: QtGui4 + 0x87956 (?winMouseButtonUp@QApplication@@SAXXZ + 0x1006)\n\t0x7ff84cd56d40: USER32 + 0x16d40 (CallWindowProcW + 0x4c0)\n\t0x7ff84cd56a1b: USER32 + 0x16a1b (CallWindowProcW + 0x19b)\n\t0x7ff84cd604d2: USER32 + 0x204d2 (IsWindowVisible + 0x1a2)\n\t0x7ff84deae6b3: ntdll + 0x9e6b3 (KiUserCallbackDispatcher + 0x23)\n\t0x7ff84aeb1163: win32u + 0x1163 (NtUserMessageCall + 0x13)\n\t0x7ff84cd546f5: USER32 + 0x146f5 (GetWindowTextW + 0x7e5)\n\t0x7ff84cd53ed1: USER32 + 0x13ed1 (UpdateWindow + 0xf1)\n\t0x7ff8487d5c09: uxtheme + 0x15c09 (HitTestThemeBackground + 0x71f9)\n\t0x7ff8487df341: uxtheme + 0x1f341 (Ordinal96 + 0x251)\n\t0x7ff8487d4a33: uxtheme + 0x14a33 (HitTestThemeBackground + 0x6023)\n\t0x7ff8487d34e0: uxtheme + 0x134e0 (HitTestThemeBackground + 0x4ad0)\n\t0x7ff84cd54413: USER32 + 0x14413 (GetWindowTextW + 0x503)\n\t 0x619fbbf7: QtGui4 + 0x4fbbf7 (?widgetDestroyed@QInputContext@@UEAAXPEAVQWidget@@@Z + 0x307)\n\t 0x61587915: QtGui4 + 0x87915 (?winMouseButtonUp@QApplication@@SAXXZ + 0xfc5)\n\t0x7ff84cd56d40: USER32 + 0x16d40 (CallWindowProcW + 0x4c0)\n\t0x7ff84cd56a1b: USER32 + 0x16a1b (CallWindowProcW + 0x19b)\n",
		"subsystem" : "unknown"
	},
	"quartus" : {
		"quartus_bits" : "64",
		"version" : "16.1.0",
		"build" : "196",
		"edition" : "Lite Edition"
	}
}